{
  "scopes": [
    {
      "name": "$XSAPPNAME.Viewer",
      "description": "Viewer"
    },
    {
      "name": "$XSAPPNAME.Admin",
      "description": "Admin"
    }
  ],
  "attributes": [
    {
      "name": "Country",
      "description": "Country",
      "valueType": "s",
      "valueRequired": false
    }
  ],
  "role-templates": [
    {
      "name": "Viewer",
      "description": "generated",
      "scope-references": [
        "$XSAPPNAME.Viewer"
      ],
      "attribute-references": []
    },
    {
      "name": "Admin",
      "description": "generated",
      "scope-references": [
        "$XSAPPNAME.Admin"
      ],
      "attribute-references": []
    },
    {
      "name": "Admin-Country",
      "description": "generated",
      "default-role-name": "Country Attribute of a User",
      "scope-references": [],
      "attribute-references": [
        "Country"
      ]
    }
  ]
}
